stardust/Stardust.py
stardust/__init__.py
stardust/utils.py
sc_stardust-0.1.2.dist-info/METADATA
sc_stardust-0.1.2.dist-info/WHEEL
sc_stardust-0.1.2.dist-info/RECORD
