Metadata-Version: 2.3
Name: sc-stardust
Version: 0.1.2
Summary: Subcellular-level Tool for the Analysis of RNA Distribution Using optimal Transport
Author: Emma Chen
Author-email: emmazhangchenn@gmail.com
Requires-Python: >=3.9,<4.0
Classifier: Programming Language :: Python :: 3
Classifier: Programming Language :: Python :: 3.9
Classifier: Programming Language :: Python :: 3.10
Classifier: Programming Language :: Python :: 3.11
Classifier: Programming Language :: Python :: 3.12
Classifier: Programming Language :: Python :: 3.13
Requires-Dist: matplotlib (==3.9.4)
Requires-Dist: networkx (==3.2.1)
Requires-Dist: numpy (==1.26.4)
Requires-Dist: ott-jax (==0.4.6)
Requires-Dist: pandas (==2.2.2)
Requires-Dist: pot (==0.9.4)
Requires-Dist: scikit-learn (==1.5.1)
Requires-Dist: scipy (==1.13.1)
Requires-Dist: sim-fish (==0.2.0)
Requires-Dist: umap-learn (==0.5.6)
